auto_blogger/__init__.py
auto_blogger/automation_engine.py
auto_blogger/css_selector_extractor.py
auto_blogger/gui_blogger.py
auto_blogger/log_manager.py
auto_blogger/configs/category_keywords.json
auto_blogger/configs/custom_seo_keywords.json
auto_blogger/configs/default.json
auto_blogger/configs/do_follow_urls.json
auto_blogger/configs/external_links.json
auto_blogger/configs/gemini_prompts.json
auto_blogger/configs/internal_links.json
auto_blogger/configs/openai_image_config.json
auto_blogger/configs/sky_sports_alternative.json
auto_blogger/configs/static_clubs.json
auto_blogger/configs/stop_words.json
auto_blogger/configs/style_prompt.json
auto_blogger/configs/tag_synonyms.json
auto_blogger/configs/test_seo_fix.json
auto_blogger/configs/vivek.json
auto_blogger/configs/weights.json
auto_blogger-1.0.0.dist-info/licenses/LICENSE
auto_blogger-1.0.0.dist-info/METADATA
auto_blogger-1.0.0.dist-info/WHEEL
auto_blogger-1.0.0.dist-info/entry_points.txt
auto_blogger-1.0.0.dist-info/top_level.txt
auto_blogger-1.0.0.dist-info/RECORD
