Metadata-Version: 2.4
Name: auto-blogger
Version: 1.0.0
Summary: Automated WordPress Blog Posting Tool with AI Integration
Home-page: https://github.com/AryanVBW/AUTO-blogger
Author: AryanVBW
Author-email: AryanVBW <AryanVBW@gmail.com>
Project-URL: Homepage, https://github.com/AryanVBW/AUTO-blogger
Project-URL: Bug Reports, https://github.com/AryanVBW/AUTO-blogger/issues
Project-URL: Source, https://github.com/AryanVBW/AUTO-blogger
Project-URL: Documentation, https://aryanvbw.github.io/AUTO-blogger/website/
Project-URL: Website, https://aryanvbw.github.io/AUTO-blogger/website/
Keywords: wordpress,blog,automation,ai,content,posting,seo
Classifier: Development Status :: 4 - Beta
Classifier: Intended Audience :: Developers
Classifier: Intended Audience :: End Users/Desktop
Classifier: Topic :: Internet :: WWW/HTTP :: Dynamic Content :: Content Management System
Classifier: Topic :: Software Development :: Libraries :: Python Modules
Classifier: License :: OSI Approved :: MIT License
Classifier: Programming Language :: Python :: 3
Classifier: Programming Language :: Python :: 3.8
Classifier: Programming Language :: Python :: 3.9
Classifier: Programming Language :: Python :: 3.10
Classifier: Programming Language :: Python :: 3.11
Classifier: Programming Language :: Python :: 3.12
Classifier: Operating System :: OS Independent
Requires-Python: >=3.8
License-File: LICENSE
Requires-Dist: requests>=2.31.0
Requires-Dist: beautifulsoup4>=4.12.0
Requires-Dist: lxml>=4.9.0
Requires-Dist: selenium>=4.15.0
Requires-Dist: webdriver-manager>=3.8.0
Requires-Dist: openai>=1.3.0
Requires-Dist: google-generativeai>=0.3.0
Requires-Dist: Pillow>=10.0.0
Requires-Dist: python-dotenv>=1.0.0
Requires-Dist: colorama>=0.4.6
Requires-Dist: tqdm>=4.66.0
Requires-Dist: validators>=0.22.0
Requires-Dist: requests-toolbelt>=0.10.1
Provides-Extra: dev
Requires-Dist: pytest>=7.4.0; extra == "dev"
Requires-Dist: pytest-cov>=4.1.0; extra == "dev"
Requires-Dist: black>=23.9.0; extra == "dev"
Requires-Dist: flake8>=6.1.0; extra == "dev"
Requires-Dist: mypy>=1.6.0; extra == "dev"
Requires-Dist: pre-commit>=3.5.0; extra == "dev"
Dynamic: author
Dynamic: home-page
Dynamic: license-file
Dynamic: requires-python
